rich_heatmap/__init__.py
rich_heatmap/heatmap.py
rich_heatmap/py.typed
rich_heatmap-0.1.3.dist-info/METADATA
rich_heatmap-0.1.3.dist-info/WHEEL
rich_heatmap-0.1.3.dist-info/licenses/LICENSE
rich_heatmap-0.1.3.dist-info/RECORD
